{"id": 64, "width": 1920, "height": 1080, "duration": 29.0, "title": "Justin Bieber - Sorry (Lyric Video)", "user": "Justin Bieber", "meta": {"description": "\u2018Purpose\u2019 Available Everywhere Now!\niTunes: http://smarturl.it/PurposeDlx?IQid=VEVO1113 \nStream & Add To Your Spotify Playlist: http://smarturl.it/sPurpose?IQid=VEVO1113 \nGoogle Play: http://smarturl.it/gPurpose?IQid=VEVO1113 \nAmazon: http://smarturl.it/aPurpose?IQid=VEVO1113 \n\nJustin Bieber - Sorry (Lyric Video)\n\nhttp://vevo.ly/hO26Lr", "categories": ["Music"], "tags": ["Justin", "Bieber", "Sorry", "(Lyric", "Video)", "Def", "Jam", "Pop", "\u30b8\u30e3\u30b9\u30c6\u30a3\u30f3\u30fb\u30d3\u30fc\u30d0\u30fc", "\uc800\uc2a4\ud2f4 \ube44\ubc84", "\u5c0f\u8cc8\u65af\u6c40", "\u8d3e\u65af\u6c40\u6bd4\u4f2f", "lyrics in"], "comments": [{"text": "Amo muito \u2764", "author": "kanandadu4061"}, {"text": "When am feeling sad i always come here,because i missed all my loved ones,especially my mother feel like seeing her and pour out all my pains and tears to her..only she can understand how am feeling..Vero my mother u broke my heart when u left me,daddy left with u as well.and my two brothers also..life isn't the same\ud83d\udc94\ud83d\udc94\ud83d\udc94\ud83d\udc94\ud83d\udc94", "author": "chris-pw5sd"}, {"text": "Kaitlyn you are very beautiful this song for you Sorry", "author": "kikaycajulao1529"}, {"text": "Oct 2024", "author": "sangitanaik1432"}, {"text": "Edit \u2764\ud83d\ude2e\ud83d\ude2e\ud83d\ude2e\ud83d\ude2e", "author": "Abdinaasir836"}, {"text": "October 2024", "author": "JunaidAnsari33344"}, {"text": "\u2764\u2764\u2764\u2764\u2764\u2764\ud83c\udde9\ud83c\uddf4", "author": "trululu4296"}, {"text": "Sorry to diddy", "author": "khadka_ff23"}, {"text": "Party and war is over my poor baby, I'm with you Justin, I know what it's like to be abused \ud83d\ude2d\ud83d\ude2d", "author": "unamaite"}]}}